{
  "fixture_name": "no_hindsight_sample_signal_replay_fixture",
  "fixture_version": 1,
  "purpose": "Shape-only fixture for Historical Signal Replay v1 schema/scaffold review.",
  "input": {
    "symbol": "SPY",
    "timestamp": "2026-04-20T15:30:00-04:00",
    "candles_1h_rth": [
      {
        "timestamp": "2026-04-20T09:30:00-04:00",
        "open": 512.1,
        "high": 514.2,
        "low": 511.6,
        "close": 513.8,
        "volume": 18425000
      },
      {
        "timestamp": "2026-04-20T10:30:00-04:00",
        "open": 513.8,
        "high": 515.1,
        "low": 513.2,
        "close": 514.7,
        "volume": 13792000
      },
      {
        "timestamp": "2026-04-20T11:30:00-04:00",
        "open": 514.7,
        "high": 515.4,
        "low": 513.9,
        "close": 514.4,
        "volume": 10188000
      },
      {
        "timestamp": "2026-04-20T12:30:00-04:00",
        "open": 514.4,
        "high": 516.0,
        "low": 514.1,
        "close": 515.8,
        "volume": 11234000
      },
      {
        "timestamp": "2026-04-20T13:30:00-04:00",
        "open": 515.8,
        "high": 516.3,
        "low": 515.0,
        "close": 515.5,
        "volume": 9456000
      },
      {
        "timestamp": "2026-04-20T14:30:00-04:00",
        "open": 515.5,
        "high": 516.8,
        "low": 515.2,
        "close": 516.4,
        "volume": 12301000
      }
    ],
    "context_24h_daily": {
      "status": "CONTEXT_24H_DAILY_UNCONFIRMED",
      "value": null,
      "as_of": null,
      "source": null
    },
    "market_calendar_session": {
      "session_date": "2026-04-20",
      "session_type": "regular",
      "is_regular_session": true,
      "timezone": "America/New_York",
      "notes": "Regular RTH sample session."
    },
    "macro_context": {
      "status": "MACRO_UNCONFIRMED",
      "value": null,
      "as_of": null,
      "source": null
    },
    "iv_context": {
      "status": "IV_UNCONFIRMED",
      "value": null,
      "as_of": null,
      "source": null
    },
    "event_context": {
      "status": "EVENT_UNCONFIRMED",
      "value": null,
      "as_of": null,
      "source": null
    }
  },
  "expected_output_shape": {
    "timestamp": "2026-04-20T15:30:00-04:00",
    "symbol": "SPY",
    "setup_type": "Continuation",
    "setup_state": "developing",
    "stage": "pending_completed_candle_approval",
    "trigger_state": "pending",
    "trigger_level": 516.8,
    "invalidation": 515.0,
    "room_status": "unconfirmed",
    "extension_status": "unconfirmed",
    "context_24h": "CONTEXT_24H_DAILY_UNCONFIRMED",
    "wall_thesis_fit": "unconfirmed",
    "final_verdict": "PENDING",
    "primary_blocker": "completed_candle_approval_required",
    "cautions_watchouts": [
      "MACRO_UNCONFIRMED",
      "IV_UNCONFIRMED",
      "EVENT_UNCONFIRMED"
    ],
    "winner_selection_result": {
      "selected_symbol": "SPY",
      "selected_setup_type": "Continuation",
      "selection_status": "shape_only_unimplemented"
    },
    "human_next_step": "Wait for completed candle confirmation before any manual decision.",
    "first_seen": "2026-04-20T14:30:00-04:00",
    "last_seen": "2026-04-20T15:30:00-04:00",
    "state_changed": true,
    "prior_state": "watching",
    "current_state": "pending",
    "trigger_changed": true,
    "blocker_changed": true,
    "duplicate_alert_suppression_key": "SPY|2026-04-20|Continuation|pending_completed_candle_approval|completed_candle_approval_required"
  }
}
